winkey/__init__.py
winkey/get.py
winkey/public.py
win_key-1.1.2.dist-info/METADATA
win_key-1.1.2.dist-info/WHEEL
win_key-1.1.2.dist-info/top_level.txt
win_key-1.1.2.dist-info/RECORD
