Metadata-Version: 2.4
Name: win-key
Version: 1.1.2
Summary: Windows系统键盘状态检测工具（轻量级，无须单独线程等）
Dynamic: description
Dynamic: summary
